har_extractor.py
har_extractor-1.0.1.dist-info/DESCRIPTION.rst
har_extractor-1.0.1.dist-info/RECORD
har_extractor-1.0.1.dist-info/WHEEL
har_extractor-1.0.1.dist-info/entry_points.txt
har_extractor-1.0.1.dist-info/top_level.txt
har_extractor-1.0.1.dist-info/METADATA
har_extractor-1.0.1.dist-info/metadata.json
