Metadata-Version: 1.2
Name: har-extractor
Version: 1.0.1
Summary: HTTP Archive extractor
Home-page: https://github.com/dead-beef/har-extractor
Author: dead-beef
Author-email: contact@dead-beef.tk
License: MIT
Keywords: har http archive extractor
Platform: UNKNOWN
Classifier: Development Status :: 5 - Production/Stable
Classifier: Environment :: Console
Classifier: Intended Audience :: End Users/Desktop
Classifier: License :: OSI Approved :: MIT License
Classifier: Programming Language :: Python :: 3
Classifier: Programming Language :: Python :: 3.4
Classifier: Topic :: Internet :: WWW/HTTP
Classifier: Topic :: System :: Archiving
Classifier: Topic :: Utilities
Requires-Python: >=3
